freeart/__init__.py
freeart/__main__.py
freeart/_version.py
freeart/setup.py
freeart/app/__init__.py
freeart/app/createfluosino.py
freeart/app/interpreter.py
freeart/app/reconsfluosino.py
freeart/app/test_.py
freeart/configuration/__init__.py
freeart/configuration/config.py
freeart/configuration/configIO.py
freeart/configuration/fileInfo.py
freeart/configuration/h5ConfigIO.py
freeart/configuration/iniConfigIO.py
freeart/configuration/setup.py
freeart/configuration/structs.py
freeart/configuration/test/__init__.py
freeart/configuration/test/testConfiguration.py
freeart/configuration/test/testIO.py
freeart/core/FreeART.cp35-win_amd64.pyd
freeart/core/__init__.py
freeart/core/setup.py
freeart/core/test/__init__.py
freeart/interpreter/__init__.py
freeart/interpreter/configinterpreter.py
freeart/interpreter/setup.py
freeart/interpreter/test/__init__.py
freeart/interpreter/test/test_angles.py
freeart/interpreter/test/test_config.py
freeart/interpreter/test/test_configinterpreter.py
freeart/interpreter/test/test_fluooutgoingray.py
freeart/interpreter/test/test_fluoprojector.py
freeart/interpreter/test/test_fluoreconstruction.py
freeart/interpreter/test/test_fluosa.py
freeart/interpreter/test/test_freeart_with_fix.py
freeart/interpreter/test/test_rayparameters.py
freeart/interpreter/test/test_tx.py
freeart/interpreter/test/utils.py
freeart/resources/__init__.py
freeart/resources/fluorescenceSetup.png
freeart/resources/fluorescenceSetup.svg
freeart/resources/fluorescenceSetup_i.png
freeart/resources/fluorescenceSetup_i.svg
freeart/resources/logo.png
freeart/test/__init__.py
freeart/test/test_units.py
freeart/test/test_version.py
freeart/unitsystem/__init__.py
freeart/unitsystem/metricsystem.py
freeart/unitsystem/setup.py
freeart/utils/__init__.py
freeart/utils/benchmark.py
freeart/utils/exampleFile.py
freeart/utils/exampleutils.py
freeart/utils/genph.py
freeart/utils/h5utils.py
freeart/utils/outgoingrayalgorithm.py
freeart-3.3.0.dist-info/DESCRIPTION.rst
freeart-3.3.0.dist-info/METADATA
freeart-3.3.0.dist-info/RECORD
freeart-3.3.0.dist-info/WHEEL
freeart-3.3.0.dist-info/entry_points.txt
freeart-3.3.0.dist-info/metadata.json
freeart-3.3.0.dist-info/top_level.txt
